mssqltoolsservice/__init__.py
mssqltoolsservice/bin/Microsoft.CSharp.dll
mssqltoolsservice/bin/Microsoft.Data.Tools.Sql.BatchParser.dll
mssqltoolsservice/bin/Microsoft.DotNet.PlatformAbstractions.dll
mssqltoolsservice/bin/Microsoft.Extensions.DependencyModel.dll
mssqltoolsservice/bin/Microsoft.SqlServer.ConnectionInfo.dll
mssqltoolsservice/bin/Microsoft.SqlServer.Management.Dmf.dll
mssqltoolsservice/bin/Microsoft.SqlServer.Management.Sdk.Sfc.dll
mssqltoolsservice/bin/Microsoft.SqlServer.Management.SmoMetadataProvider.dll
mssqltoolsservice/bin/Microsoft.SqlServer.Management.SqlScriptPublishModel.dll
mssqltoolsservice/bin/Microsoft.SqlServer.Smo.dll
mssqltoolsservice/bin/Microsoft.SqlServer.SmoExtended.dll
mssqltoolsservice/bin/Microsoft.SqlServer.SqlEnum.dll
mssqltoolsservice/bin/Microsoft.SqlServer.SqlParser.dll
mssqltoolsservice/bin/Microsoft.SqlTools.Hosting.dll
mssqltoolsservice/bin/Microsoft.SqlTools.Hosting.pdb
mssqltoolsservice/bin/Microsoft.VisualBasic.dll
mssqltoolsservice/bin/Microsoft.Win32.Primitives.dll
mssqltoolsservice/bin/Microsoft.Win32.Registry.dll
mssqltoolsservice/bin/MicrosoftSqlToolsCredentials.dll
mssqltoolsservice/bin/MicrosoftSqlToolsCredentials.pdb
mssqltoolsservice/bin/MicrosoftSqlToolsServiceLayer
mssqltoolsservice/bin/MicrosoftSqlToolsServiceLayer.deps.json
mssqltoolsservice/bin/MicrosoftSqlToolsServiceLayer.dll
mssqltoolsservice/bin/MicrosoftSqlToolsServiceLayer.pdb
mssqltoolsservice/bin/MicrosoftSqlToolsServiceLayer.runtimeconfig.json
mssqltoolsservice/bin/NetCoreGlobalization.dll
mssqltoolsservice/bin/Newtonsoft.Json.dll
mssqltoolsservice/bin/SOS.NETCore.dll
mssqltoolsservice/bin/SQL SERVER 2016 TSQL Language Service EULA.RTF
mssqltoolsservice/bin/SQL SERVER V.Next SMO EULA.RTF
mssqltoolsservice/bin/System.AppContext.dll
mssqltoolsservice/bin/System.Buffers.dll
mssqltoolsservice/bin/System.Collections.Concurrent.dll
mssqltoolsservice/bin/System.Collections.Immutable.dll
mssqltoolsservice_Debian_8-1.0.0a20.dist-info/DESCRIPTION.rst
mssqltoolsservice_Debian_8-1.0.0a20.dist-info/LICENSE.txt
mssqltoolsservice_Debian_8-1.0.0a20.dist-info/METADATA
mssqltoolsservice_Debian_8-1.0.0a20.dist-info/RECORD
mssqltoolsservice_Debian_8-1.0.0a20.dist-info/WHEEL
mssqltoolsservice_Debian_8-1.0.0a20.dist-info/metadata.json
mssqltoolsservice_Debian_8-1.0.0a20.dist-info/top_level.txt
mssqltoolsservice_Debian_8-1.0.0a20.dist-info/zip-safe
